LICENSE
README.rst
console/dummy_oauth2_server.py
coub_api/__init__.py
coub_api/_urls.py
coub_api/api.py
coub_api/modules/__init__.py
coub_api/modules/base.py
coub_api/modules/channel.py
coub_api/modules/coubs.py
coub_api/modules/follows.py
coub_api/modules/friends.py
coub_api/modules/likes.py
coub_api/modules/metadata.py
coub_api/modules/notifications.py
coub_api/modules/recoub.py
coub_api/modules/search.py
coub_api/modules/timelines.py
coub_api/modules/user.py
coub_api/schemas/__init__.py
coub_api/schemas/channel.py
coub_api/schemas/constants.py
coub_api/schemas/coub.py
coub_api/schemas/friends.py
coub_api/schemas/metadata.py
coub_api/schemas/search.py
coub_api/schemas/timeline.py
coub_api/schemas/users.py
coub_api-0.3.0.dist-info/entry_points.txt
coub_api-0.3.0.dist-info/LICENSE
coub_api-0.3.0.dist-info/WHEEL
coub_api-0.3.0.dist-info/METADATA
coub_api-0.3.0.dist-info/RECORD
