Metadata-Version: 2.1
Name: coub-api
Version: 0.3.0
Summary: Api wrapper for coub.com
Home-page: https://github.com/Derfirm/coub_api
License: MIT
Keywords: coub,coub-api,api-wrapper
Author: Andrew Grinevich
Author-email: andrew.grinevich@gmail.com
Requires-Python: >=3.6,<4.0
Classifier: Development Status :: 2 - Pre-Alpha
Classifier: Intended Audience :: Information Technology
Classifier: License :: OSI Approved :: MIT License
Classifier: Natural Language :: English
Classifier: Operating System :: OS Independent
Classifier: Programming Language :: Python
Classifier: Programming Language :: Python :: 3
Classifier: Programming Language :: Python :: 3.6
Classifier: Programming Language :: Python :: 3.7
Classifier: Topic :: Internet :: WWW/HTTP
Classifier: Topic :: Software Development :: Libraries :: Python Modules
Requires-Dist: pydantic
Project-URL: Repository, https://github.com/Derfirm/coub_api
